Binary_Search_Trees/BST.py
Binary_Search_Trees/__init__.py
Binary_Search_Trees-1.0.2.dist-info/LICENSE
Binary_Search_Trees-1.0.2.dist-info/METADATA
Binary_Search_Trees-1.0.2.dist-info/WHEEL
Binary_Search_Trees-1.0.2.dist-info/top_level.txt
Binary_Search_Trees-1.0.2.dist-info/RECORD
