Metadata-Version: 2.1
Name: Binary-Search-Trees
Version: 1.0.2
Summary: Contains Methods for operations in Binary Search Tree
Home-page: https://github.com/sagar-ML-Developer/Binary_Search_Trees
Author: Himanshu Sagar
Author-email: sagarhimanshu355@gmail.com
License: MIT
Keywords: Binary_Search_Trees bst BST binarysearchtree binarytree BinarySearchTrees
Platform: UNKNOWN
Classifier: Development Status :: 5 - Production/Stable
Classifier: Intended Audience :: Developers
Classifier: Operating System :: OS Independent
Classifier: License :: OSI Approved :: MIT License
Classifier: Programming Language :: Python :: 3
Classifier: Programming Language :: Python :: 3.6
Classifier: Programming Language :: Python :: 3.7
Classifier: Programming Language :: Python :: 3.8
Requires-Python: >=3.6
Requires-Dist: multipledispatch
